{
    "Ar36": {
        "error": 9.925955844331094e-05,
        "error_type": "",
        "fit": "Bracketing Interpolate",
        "references": [
            {
                "exclude": "ok",
                "record_id": "bu-AC-A-3128",
                "uuid": "d46c3162-a1a5-482e-8bfb-1f55f8b399a9"
            },
            {
                "exclude": "ok",
                "record_id": "bu-AC-A-3129",
                "uuid": "4b7e88b8-6017-4de0-9bb5-69ca79ba9bf8"
            },
            {
                "exclude": "ok",
                "record_id": "bu-AC-A-3130",
                "uuid": "f1124e48-8252-4e2b-86bd-1a199acdc516"
            },
            {
                "exclude": "ok",
                "record_id": "bu-AC-A-3131",
                "uuid": "36945003-1a76-42de-b8dd-0602cb899b71"
            },
            {
                "exclude": "ok",
                "record_id": "bu-AC-A-3132",
                "uuid": "7c71cc59-612b-465e-b6e8-b12939c1b4c3"
            },
            {
                "exclude": "ok",
                "record_id": "bu-AC-A-3133",
                "uuid": "b78dacdf-a8de-4cfd-98e9-9e624457bb9c"
            },
            {
                "exclude": "ok",
                "record_id": "bu-AC-A-3134",
                "uuid": "225a70c5-3a7e-4a89-a71b-4a669dda862e"
            },
            {
                "exclude": "ok",
                "record_id": "bu-AC-A-3135",
                "uuid": "5e5171b8-0270-4aad-9bfb-9e396d1c2fa7"
            },
            {
                "exclude": "ok",
                "record_id": "bu-AC-A-3136",
                "uuid": "81172545-3216-4cd9-a631-a4770543ec7b"
            },
            {
                "exclude": "ok",
                "record_id": "bu-AC-A-3137",
                "uuid": "5acb36c0-06a3-4f23-8d42-be0f09732f29"
            },
            {
                "exclude": "ok",
                "record_id": "bu-AC-A-3138",
                "uuid": "f7228816-1d39-4e5c-945c-fd66a0977390"
            },
            {
                "exclude": "ok",
                "record_id": "bu-AC-A-3139",
                "uuid": "e1622491-7d46-4973-bc6f-b9f0bf1e1a1e"
            },
            {
                "exclude": "ok",
                "record_id": "bu-AC-A-3140",
                "uuid": "acd841fd-840b-4283-92a5-dada723295c1"
            },
            {
                "exclude": "ok",
                "record_id": "bu-AC-A-3141",
                "uuid": "2d1da17d-86e8-444a-8028-8023bf18730d"
            },
            {
                "exclude": "ok",
                "record_id": "bu-AC-A-3142",
                "uuid": "1c88e89e-cf38-4150-ab9d-fcb0cc48dd37"
            },
            {
                "exclude": "ok",
                "record_id": "bu-AC-A-3143",
                "uuid": "94aa7f5c-f905-404b-9b8e-494eb291e07e"
            },
            {
                "exclude": "ok",
                "record_id": "bu-AC-A-3144",
                "uuid": "d5746674-e759-4f44-ac9f-9c7b31f77430"
            },
            {
                "exclude": "ok",
                "record_id": "bu-AC-A-3145",
                "uuid": "35d02b31-75e6-4683-a996-9bc0c34a553a"
            },
            {
                "exclude": "ok",
                "record_id": "bu-AC-A-3146",
                "uuid": "c6d36cc3-e5bf-4315-9100-e0cab985e7ae"
            },
            {
                "exclude": "ok",
                "record_id": "bu-AC-A-3147",
                "uuid": "2bd99744-013f-41cf-83cb-5363a70c081a"
            },
            {
                "exclude": "ok",
                "record_id": "bu-AC-A-3148",
                "uuid": "ed135c42-8dae-4a3e-b53e-3665a9332a36"
            },
            {
                "exclude": "ok",
                "record_id": "bu-AC-A-3149",
                "uuid": "e9b2f0c6-d5b1-45ee-9d35-8ce23ecebb2b"
            }
        ],
        "reviewed": true,
        "value": 0.01200270777579578
    },
    "Ar37": {
        "error": 0.002817590021964968,
        "error_type": "",
        "fit": "Bracketing Interpolate",
        "references": [
            {
                "exclude": "ok",
                "record_id": "bu-AC-A-3128",
                "uuid": "d46c3162-a1a5-482e-8bfb-1f55f8b399a9"
            },
            {
                "exclude": "ok",
                "record_id": "bu-AC-A-3129",
                "uuid": "4b7e88b8-6017-4de0-9bb5-69ca79ba9bf8"
            },
            {
                "exclude": "ok",
                "record_id": "bu-AC-A-3130",
                "uuid": "f1124e48-8252-4e2b-86bd-1a199acdc516"
            },
            {
                "exclude": "ok",
                "record_id": "bu-AC-A-3131",
                "uuid": "36945003-1a76-42de-b8dd-0602cb899b71"
            },
            {
                "exclude": "ok",
                "record_id": "bu-AC-A-3132",
                "uuid": "7c71cc59-612b-465e-b6e8-b12939c1b4c3"
            },
            {
                "exclude": "ok",
                "record_id": "bu-AC-A-3133",
                "uuid": "b78dacdf-a8de-4cfd-98e9-9e624457bb9c"
            },
            {
                "exclude": "ok",
                "record_id": "bu-AC-A-3134",
                "uuid": "225a70c5-3a7e-4a89-a71b-4a669dda862e"
            },
            {
                "exclude": "ok",
                "record_id": "bu-AC-A-3135",
                "uuid": "5e5171b8-0270-4aad-9bfb-9e396d1c2fa7"
            },
            {
                "exclude": "ok",
                "record_id": "bu-AC-A-3136",
                "uuid": "81172545-3216-4cd9-a631-a4770543ec7b"
            },
            {
                "exclude": "ok",
                "record_id": "bu-AC-A-3137",
                "uuid": "5acb36c0-06a3-4f23-8d42-be0f09732f29"
            },
            {
                "exclude": "ok",
                "record_id": "bu-AC-A-3138",
                "uuid": "f7228816-1d39-4e5c-945c-fd66a0977390"
            },
            {
                "exclude": "ok",
                "record_id": "bu-AC-A-3139",
                "uuid": "e1622491-7d46-4973-bc6f-b9f0bf1e1a1e"
            },
            {
                "exclude": "ok",
                "record_id": "bu-AC-A-3140",
                "uuid": "acd841fd-840b-4283-92a5-dada723295c1"
            },
            {
                "exclude": "ok",
                "record_id": "bu-AC-A-3141",
                "uuid": "2d1da17d-86e8-444a-8028-8023bf18730d"
            },
            {
                "exclude": "ok",
                "record_id": "bu-AC-A-3142",
                "uuid": "1c88e89e-cf38-4150-ab9d-fcb0cc48dd37"
            },
            {
                "exclude": "ok",
                "record_id": "bu-AC-A-3143",
                "uuid": "94aa7f5c-f905-404b-9b8e-494eb291e07e"
            },
            {
                "exclude": "ok",
                "record_id": "bu-AC-A-3144",
                "uuid": "d5746674-e759-4f44-ac9f-9c7b31f77430"
            },
            {
                "exclude": "ok",
                "record_id": "bu-AC-A-3145",
                "uuid": "35d02b31-75e6-4683-a996-9bc0c34a553a"
            },
            {
                "exclude": "ok",
                "record_id": "bu-AC-A-3146",
                "uuid": "c6d36cc3-e5bf-4315-9100-e0cab985e7ae"
            },
            {
                "exclude": "ok",
                "record_id": "bu-AC-A-3147",
                "uuid": "2bd99744-013f-41cf-83cb-5363a70c081a"
            },
            {
                "exclude": "ok",
                "record_id": "bu-AC-A-3148",
                "uuid": "ed135c42-8dae-4a3e-b53e-3665a9332a36"
            },
            {
                "exclude": "ok",
                "record_id": "bu-AC-A-3149",
                "uuid": "e9b2f0c6-d5b1-45ee-9d35-8ce23ecebb2b"
            }
        ],
        "reviewed": true,
        "value": 0.02495050192429573
    },
    "Ar38": {
        "error": 0.006984400244951014,
        "error_type": "",
        "fit": "Bracketing Interpolate",
        "references": [
            {
                "exclude": "ok",
                "record_id": "bu-AC-A-3128",
                "uuid": "d46c3162-a1a5-482e-8bfb-1f55f8b399a9"
            },
            {
                "exclude": "ok",
                "record_id": "bu-AC-A-3129",
                "uuid": "4b7e88b8-6017-4de0-9bb5-69ca79ba9bf8"
            },
            {
                "exclude": "ok",
                "record_id": "bu-AC-A-3130",
                "uuid": "f1124e48-8252-4e2b-86bd-1a199acdc516"
            },
            {
                "exclude": "ok",
                "record_id": "bu-AC-A-3131",
                "uuid": "36945003-1a76-42de-b8dd-0602cb899b71"
            },
            {
                "exclude": "ok",
                "record_id": "bu-AC-A-3132",
                "uuid": "7c71cc59-612b-465e-b6e8-b12939c1b4c3"
            },
            {
                "exclude": "ok",
                "record_id": "bu-AC-A-3133",
                "uuid": "b78dacdf-a8de-4cfd-98e9-9e624457bb9c"
            },
            {
                "exclude": "ok",
                "record_id": "bu-AC-A-3134",
                "uuid": "225a70c5-3a7e-4a89-a71b-4a669dda862e"
            },
            {
                "exclude": "ok",
                "record_id": "bu-AC-A-3135",
                "uuid": "5e5171b8-0270-4aad-9bfb-9e396d1c2fa7"
            },
            {
                "exclude": "ok",
                "record_id": "bu-AC-A-3136",
                "uuid": "81172545-3216-4cd9-a631-a4770543ec7b"
            },
            {
                "exclude": "ok",
                "record_id": "bu-AC-A-3137",
                "uuid": "5acb36c0-06a3-4f23-8d42-be0f09732f29"
            },
            {
                "exclude": "ok",
                "record_id": "bu-AC-A-3138",
                "uuid": "f7228816-1d39-4e5c-945c-fd66a0977390"
            },
            {
                "exclude": "ok",
                "record_id": "bu-AC-A-3139",
                "uuid": "e1622491-7d46-4973-bc6f-b9f0bf1e1a1e"
            },
            {
                "exclude": "ok",
                "record_id": "bu-AC-A-3140",
                "uuid": "acd841fd-840b-4283-92a5-dada723295c1"
            },
            {
                "exclude": "ok",
                "record_id": "bu-AC-A-3141",
                "uuid": "2d1da17d-86e8-444a-8028-8023bf18730d"
            },
            {
                "exclude": "ok",
                "record_id": "bu-AC-A-3142",
                "uuid": "1c88e89e-cf38-4150-ab9d-fcb0cc48dd37"
            },
            {
                "exclude": "ok",
                "record_id": "bu-AC-A-3143",
                "uuid": "94aa7f5c-f905-404b-9b8e-494eb291e07e"
            },
            {
                "exclude": "ok",
                "record_id": "bu-AC-A-3144",
                "uuid": "d5746674-e759-4f44-ac9f-9c7b31f77430"
            },
            {
                "exclude": "ok",
                "record_id": "bu-AC-A-3145",
                "uuid": "35d02b31-75e6-4683-a996-9bc0c34a553a"
            },
            {
                "exclude": "ok",
                "record_id": "bu-AC-A-3146",
                "uuid": "c6d36cc3-e5bf-4315-9100-e0cab985e7ae"
            },
            {
                "exclude": "ok",
                "record_id": "bu-AC-A-3147",
                "uuid": "2bd99744-013f-41cf-83cb-5363a70c081a"
            },
            {
                "exclude": "ok",
                "record_id": "bu-AC-A-3148",
                "uuid": "ed135c42-8dae-4a3e-b53e-3665a9332a36"
            },
            {
                "exclude": "ok",
                "record_id": "bu-AC-A-3149",
                "uuid": "e9b2f0c6-d5b1-45ee-9d35-8ce23ecebb2b"
            }
        ],
        "reviewed": true,
        "value": 0.0027252228188824577
    },
    "Ar39": {
        "error": 0.004808853965590011,
        "error_type": "",
        "fit": "Bracketing Interpolate",
        "references": [
            {
                "exclude": "ok",
                "record_id": "bu-AC-A-3128",
                "uuid": "d46c3162-a1a5-482e-8bfb-1f55f8b399a9"
            },
            {
                "exclude": "ok",
                "record_id": "bu-AC-A-3129",
                "uuid": "4b7e88b8-6017-4de0-9bb5-69ca79ba9bf8"
            },
            {
                "exclude": "ok",
                "record_id": "bu-AC-A-3130",
                "uuid": "f1124e48-8252-4e2b-86bd-1a199acdc516"
            },
            {
                "exclude": "ok",
                "record_id": "bu-AC-A-3131",
                "uuid": "36945003-1a76-42de-b8dd-0602cb899b71"
            },
            {
                "exclude": "ok",
                "record_id": "bu-AC-A-3132",
                "uuid": "7c71cc59-612b-465e-b6e8-b12939c1b4c3"
            },
            {
                "exclude": "ok",
                "record_id": "bu-AC-A-3133",
                "uuid": "b78dacdf-a8de-4cfd-98e9-9e624457bb9c"
            },
            {
                "exclude": "ok",
                "record_id": "bu-AC-A-3134",
                "uuid": "225a70c5-3a7e-4a89-a71b-4a669dda862e"
            },
            {
                "exclude": "ok",
                "record_id": "bu-AC-A-3135",
                "uuid": "5e5171b8-0270-4aad-9bfb-9e396d1c2fa7"
            },
            {
                "exclude": "ok",
                "record_id": "bu-AC-A-3136",
                "uuid": "81172545-3216-4cd9-a631-a4770543ec7b"
            },
            {
                "exclude": "ok",
                "record_id": "bu-AC-A-3137",
                "uuid": "5acb36c0-06a3-4f23-8d42-be0f09732f29"
            },
            {
                "exclude": "ok",
                "record_id": "bu-AC-A-3138",
                "uuid": "f7228816-1d39-4e5c-945c-fd66a0977390"
            },
            {
                "exclude": "ok",
                "record_id": "bu-AC-A-3139",
                "uuid": "e1622491-7d46-4973-bc6f-b9f0bf1e1a1e"
            },
            {
                "exclude": "ok",
                "record_id": "bu-AC-A-3140",
                "uuid": "acd841fd-840b-4283-92a5-dada723295c1"
            },
            {
                "exclude": "ok",
                "record_id": "bu-AC-A-3141",
                "uuid": "2d1da17d-86e8-444a-8028-8023bf18730d"
            },
            {
                "exclude": "ok",
                "record_id": "bu-AC-A-3142",
                "uuid": "1c88e89e-cf38-4150-ab9d-fcb0cc48dd37"
            },
            {
                "exclude": "ok",
                "record_id": "bu-AC-A-3143",
                "uuid": "94aa7f5c-f905-404b-9b8e-494eb291e07e"
            },
            {
                "exclude": "ok",
                "record_id": "bu-AC-A-3144",
                "uuid": "d5746674-e759-4f44-ac9f-9c7b31f77430"
            },
            {
                "exclude": "ok",
                "record_id": "bu-AC-A-3145",
                "uuid": "35d02b31-75e6-4683-a996-9bc0c34a553a"
            },
            {
                "exclude": "ok",
                "record_id": "bu-AC-A-3146",
                "uuid": "c6d36cc3-e5bf-4315-9100-e0cab985e7ae"
            },
            {
                "exclude": "ok",
                "record_id": "bu-AC-A-3147",
                "uuid": "2bd99744-013f-41cf-83cb-5363a70c081a"
            },
            {
                "exclude": "ok",
                "record_id": "bu-AC-A-3148",
                "uuid": "ed135c42-8dae-4a3e-b53e-3665a9332a36"
            },
            {
                "exclude": "ok",
                "record_id": "bu-AC-A-3149",
                "uuid": "e9b2f0c6-d5b1-45ee-9d35-8ce23ecebb2b"
            }
        ],
        "reviewed": true,
        "value": 0.007825154409378667
    },
    "Ar40": {
        "error": 0.011144740340481553,
        "error_type": "",
        "fit": "Bracketing Interpolate",
        "references": [
            {
                "exclude": "ok",
                "record_id": "bu-AC-A-3128",
                "uuid": "d46c3162-a1a5-482e-8bfb-1f55f8b399a9"
            },
            {
                "exclude": "ok",
                "record_id": "bu-AC-A-3129",
                "uuid": "4b7e88b8-6017-4de0-9bb5-69ca79ba9bf8"
            },
            {
                "exclude": "ok",
                "record_id": "bu-AC-A-3130",
                "uuid": "f1124e48-8252-4e2b-86bd-1a199acdc516"
            },
            {
                "exclude": "ok",
                "record_id": "bu-AC-A-3131",
                "uuid": "36945003-1a76-42de-b8dd-0602cb899b71"
            },
            {
                "exclude": "ok",
                "record_id": "bu-AC-A-3132",
                "uuid": "7c71cc59-612b-465e-b6e8-b12939c1b4c3"
            },
            {
                "exclude": "ok",
                "record_id": "bu-AC-A-3133",
                "uuid": "b78dacdf-a8de-4cfd-98e9-9e624457bb9c"
            },
            {
                "exclude": "ok",
                "record_id": "bu-AC-A-3134",
                "uuid": "225a70c5-3a7e-4a89-a71b-4a669dda862e"
            },
            {
                "exclude": "ok",
                "record_id": "bu-AC-A-3135",
                "uuid": "5e5171b8-0270-4aad-9bfb-9e396d1c2fa7"
            },
            {
                "exclude": "ok",
                "record_id": "bu-AC-A-3136",
                "uuid": "81172545-3216-4cd9-a631-a4770543ec7b"
            },
            {
                "exclude": "ok",
                "record_id": "bu-AC-A-3137",
                "uuid": "5acb36c0-06a3-4f23-8d42-be0f09732f29"
            },
            {
                "exclude": "ok",
                "record_id": "bu-AC-A-3138",
                "uuid": "f7228816-1d39-4e5c-945c-fd66a0977390"
            },
            {
                "exclude": "ok",
                "record_id": "bu-AC-A-3139",
                "uuid": "e1622491-7d46-4973-bc6f-b9f0bf1e1a1e"
            },
            {
                "exclude": "ok",
                "record_id": "bu-AC-A-3140",
                "uuid": "acd841fd-840b-4283-92a5-dada723295c1"
            },
            {
                "exclude": "ok",
                "record_id": "bu-AC-A-3141",
                "uuid": "2d1da17d-86e8-444a-8028-8023bf18730d"
            },
            {
                "exclude": "ok",
                "record_id": "bu-AC-A-3142",
                "uuid": "1c88e89e-cf38-4150-ab9d-fcb0cc48dd37"
            },
            {
                "exclude": "ok",
                "record_id": "bu-AC-A-3143",
                "uuid": "94aa7f5c-f905-404b-9b8e-494eb291e07e"
            },
            {
                "exclude": "ok",
                "record_id": "bu-AC-A-3144",
                "uuid": "d5746674-e759-4f44-ac9f-9c7b31f77430"
            },
            {
                "exclude": "ok",
                "record_id": "bu-AC-A-3145",
                "uuid": "35d02b31-75e6-4683-a996-9bc0c34a553a"
            },
            {
                "exclude": "ok",
                "record_id": "bu-AC-A-3146",
                "uuid": "c6d36cc3-e5bf-4315-9100-e0cab985e7ae"
            },
            {
                "exclude": "ok",
                "record_id": "bu-AC-A-3147",
                "uuid": "2bd99744-013f-41cf-83cb-5363a70c081a"
            },
            {
                "exclude": "ok",
                "record_id": "bu-AC-A-3148",
                "uuid": "ed135c42-8dae-4a3e-b53e-3665a9332a36"
            },
            {
                "exclude": "ok",
                "record_id": "bu-AC-A-3149",
                "uuid": "e9b2f0c6-d5b1-45ee-9d35-8ce23ecebb2b"
            }
        ],
        "reviewed": true,
        "value": 3.413696176550384
    },
    "Ar41": {
        "error": 0.00871030029995464,
        "error_type": "",
        "fit": "previous",
        "references": [
            {
                "exclude": false,
                "record_id": "bu-AC-A-3146"
            }
        ],
        "value": 0.006459536229490109
    }
}